MANIFEST.in
README.md
requirements.txt
setup.py
joker/cast/__init__.py
joker/cast/collective.py
joker/cast/iterative.py
joker/cast/numeric.py
joker/cast/syntax.py
joker/cast/timedate.py
joker_cast.egg-info/PKG-INFO
joker_cast.egg-info/SOURCES.txt
joker_cast.egg-info/dependency_links.txt
joker_cast.egg-info/namespace_packages.txt
joker_cast.egg-info/not-zip-safe
joker_cast.egg-info/requires.txt
joker_cast.egg-info/top_level.txt